klean/__init__.py
klean/main.py
klean-0.1.0.dist-info/METADATA
klean-0.1.0.dist-info/WHEEL
klean-0.1.0.dist-info/RECORD
